jpyc_core_sdk/__init__.py
jpyc_core_sdk/client.py
jpyc_core_sdk/jpyc.py
jpyc_core_sdk/artifacts/v2.json
jpyc_core_sdk/interfaces/__init__.py
jpyc_core_sdk/interfaces/client.py
jpyc_core_sdk/interfaces/jpyc.py
jpyc_core_sdk/utils/__init__.py
jpyc_core_sdk/utils/addresses.py
jpyc_core_sdk/utils/artifacts.py
jpyc_core_sdk/utils/chains.py
jpyc_core_sdk/utils/constants.py
jpyc_core_sdk/utils/currencies.py
jpyc_core_sdk/utils/errors.py
jpyc_core_sdk/utils/types.py
jpyc_core_sdk/utils/validators.py
jpyc_core_sdk-1.0.5.dist-info/licenses/LICENSE
jpyc_core_sdk-1.0.5.dist-info/METADATA
jpyc_core_sdk-1.0.5.dist-info/WHEEL
jpyc_core_sdk-1.0.5.dist-info/top_level.txt
jpyc_core_sdk-1.0.5.dist-info/RECORD
