Metadata-Version: 2.4
Name: jpyc-core-sdk
Version: 1.0.5
Summary: A Python SDK for interacting with JPYCv2 contracts
Author-email: SeiyaKobayashi <eng@seiya.work>, mameta <mameta.zk@gmail.com>
Maintainer-email: SeiyaKobayashi <eng@seiya.work>, mameta <mameta.zk@gmail.com>
License-Expression: MIT
Project-URL: repository, https://github.com/jcam1/python-sdk
Project-URL: documentation, https://github.com/jcam1/python-sdk/tree/main/docs/core
Project-URL: Bug Tracker, https://github.com/jcam1/python-sdk/issues/new?template=bug_report.md
Keywords: jpyc,jpy,stablecoin,ethereum,evm,erc20,blockchain,web3py
Classifier: Development Status :: 4 - Beta
Classifier: Intended Audience :: Developers
Classifier: Programming Language :: Python :: 3
Classifier: Programming Language :: Python :: 3.12
Classifier: Programming Language :: Python :: 3.13
Classifier: Programming Language :: Python :: 3.14
Classifier: Programming Language :: Python :: 3.15
Classifier: Topic :: Software Development :: Libraries
Classifier: Topic :: Software Development :: Libraries :: Python Modules
Requires-Python: >=3.12
License-File: LICENSE
Requires-Dist: eth-typing>=5.2.1
Requires-Dist: pydantic>=2.11.4
Requires-Dist: web3>=7.11.0
Dynamic: license-file
